clagiordano/__init__.py
clagiordano/python3_logger/AbstractLogger.py
clagiordano/python3_logger/CLILogger.py
clagiordano/python3_logger/LogLevels.py
clagiordano/python3_logger/__init__.py
clagiordano.python3_logger-1.1.0.dist-info/WHEEL
clagiordano.python3_logger-1.1.0.dist-info/METADATA
clagiordano.python3_logger-1.1.0.dist-info/RECORD
