Metadata-Version: 2.1
Name: clagiordano.python3-logger
Version: 1.1.0
Summary: Library for logging facility
Home-page: https://github.com/clagiordano/python3-logger
License: LGPL-3.0-or-later
Keywords: clagiordano,logger,cli,tool,utility
Author: Claudio Giordano
Author-email: claudio.giordano@autistici.org
Requires-Python: >=3.5,<4.0
Classifier: License :: OSI Approved :: GNU Lesser General Public License v3 or later (LGPLv3+)
Classifier: Programming Language :: Python :: 3
Classifier: Programming Language :: Python :: 3.10
Classifier: Programming Language :: Python :: 3.5
Classifier: Programming Language :: Python :: 3.6
Classifier: Programming Language :: Python :: 3.7
Classifier: Programming Language :: Python :: 3.8
Classifier: Programming Language :: Python :: 3.9
Project-URL: Repository, https://github.com/clagiordano/python3-logger
